<meta>
    <script src = "loader.lua" type = "client" cache = "false" />

    <!-- Ide írd be sorba a fájlokat, txd, dff-->
    <file src = "skins/138.txd" />
    <file src = "skins/138.dff" />
    <file src = "skins/139.txd" />
    <file src = "skins/139.dff" />
    <file src = "skins/140.txd" />
    <file src = "skins/140.dff" />
    <file src = "skins/202.txd" />
    <file src = "skins/202.dff" />
    <file src = "skins/248.txd" />
    <file src = "skins/248.dff" />
    <file src = "skins/251.txd" />
    <file src = "skins/251.dff" />
</meta>